{
    "app":{
        "name": "Lead",
        "ajax":null,
        "paths":{
            "*":"http://54.83.28.108/lead/node/",
            "api": "http://54.83.28.108/lead/node/api/",
            "sql": "http://54.83.28.108/lead/node/model/sql/"
        }
    },
    "mods":{
        "webServer":{
            "mod":"web",
            "allowOrigin":"*",
            "delimiter":["&"],
            "uploadWL":[]
        },
        "mainDb":{
            "mod":"mysql",
            "database":"lead",
            "instance":"small",
            "character":"utf8_general_ci",
            "collate":"utf8_bin"
        },
        "mainCache":{
            "mod":"redis",
            "instance":"small"
        }
    },
    "mysql":{
        "remarks":"use json schema validator, https://github.com/epoberezkin/ajv",
        "mainDB":{
            "users":{
                "un":["VARCHAR(16)"],
                "pwd":["INT"],
                "type":["VARCHAR(16)"],
                "session":["VARCHAR(16)"],
                "token":["VARCHAR(16)"],
                "platform":["VARCHAR(16)"],
                "locks":["list"],
                "UNIQUE":[["hms_uid", "domain"]],
                "INDEX":[["token"],["seen_at"]]
            },
            "domains":{
                "REF":[["users"]]
            },
            "locks":{
                "type":"INT NOT NULL",
                "LIST":['chatMsg','recipients'],
                "REF":[["users"],["LIST","users"]]
            },
            "logs":{
            }
        }
    }
}
